ddg/__init__.py
ddg/apiDDG.py
duckduckgo_search_api-0.1.5.dist-info/LICENSE
duckduckgo_search_api-0.1.5.dist-info/METADATA
duckduckgo_search_api-0.1.5.dist-info/WHEEL
duckduckgo_search_api-0.1.5.dist-info/top_level.txt
duckduckgo_search_api-0.1.5.dist-info/RECORD
