Metadata-Version: 2.1
Name: duckduckgo_search_api
Version: 0.1.5
Summary: A simple and lightweight Python wrapper for DuckDuckGo search.
Home-page: https://github.com/giaco8020/duckduckgo-search-api
Author: giaco8020
Classifier: Programming Language :: Python :: 3
Classifier: License :: OSI Approved :: MIT License
Classifier: Operating System :: OS Independent
Requires-Python: >=3.6
License-File: LICENSE
Requires-Dist: requests>=2.24.0
Requires-Dist: beautifulsoup4>=4.9.3
Provides-Extra: dev
Requires-Dist: pytest>=3.7; extra == "dev"
